helphelp/__init__.py
helphelp-2.0.1.dist-info/METADATA
helphelp-2.0.1.dist-info/WHEEL
helphelp-2.0.1.dist-info/entry_points.txt
helphelp-2.0.1.dist-info/top_level.txt
helphelp-2.0.1.dist-info/RECORD
