Metadata-Version: 2.1
Name: helphelp
Version: 2.0.1
Summary: man-like tool to get online help on Python modules, classes and functions
Home-page: https://github.com/hamelin/helphelp/
Author: Benoit Hamelin
Author-email: benoit@benoithamelin.com
License: UNKNOWN
Platform: UNKNOWN
Requires-Dist: nestedtext
